diacamma/__init__.py
diacamma/microbusiness/__init__.py
diacamma/microbusiness/build
diacamma/microbusiness/models.py
diacamma/microbusiness/tests.py
diacamma/microbusiness/views.py
diacamma/microbusiness/locale/en/LC_MESSAGES/django.mo
diacamma/microbusiness/locale/en/LC_MESSAGES/django.po
diacamma/microbusiness/locale/fr/LC_MESSAGES/django.mo
diacamma/microbusiness/locale/fr/LC_MESSAGES/django.po
diacamma/microbusiness/migrations/0001_initial.py
diacamma/microbusiness/migrations/__init__.py
diacamma/microbusiness/migrations/__pycache__/0001_initial.cpython-39.pyc
diacamma/microbusiness/migrations/__pycache__/__init__.cpython-39.pyc
diacamma/microbusiness/static/diacamma.microbusiness/images/empty
diacamma/pro/Diacamma.ico
diacamma/pro/Diacamma.jpg
diacamma/pro/Diacamma.png
diacamma/pro/DiacammaPro.ico
diacamma/pro/DiacammaPro.jpg
diacamma/pro/DiacammaPro.png
diacamma/pro/__init__.py
diacamma/pro/appli_settings.py
diacamma/pro/build
diacamma/pro/diacamma_pro.css
diacamma/pro/init_french.csv
diacamma/pro/tests.py
diacamma/pro/views.py
diacamma/pro/docs/build_en/doctrees/environment.pickle
diacamma/pro/docs/build_en/doctrees/first_step.doctree
diacamma/pro/docs/build_en/doctrees/index.doctree
diacamma/pro/docs/build_en/doctrees/presentation.doctree
diacamma/pro/docs/build_fr/doctrees/environment.pickle
diacamma/pro/docs/build_fr/doctrees/first_step.doctree
diacamma/pro/docs/build_fr/doctrees/index.doctree
diacamma/pro/docs/build_fr/doctrees/presentation.doctree
diacamma/pro/docs/en/Makefile
diacamma/pro/docs/en/conf.py
diacamma/pro/docs/en/first_step.rst
diacamma/pro/docs/en/index.rst
diacamma/pro/docs/en/presentation.rst
diacamma/pro/docs/fr/Makefile
diacamma/pro/docs/fr/conf.py
diacamma/pro/docs/fr/first_step.rst
diacamma/pro/docs/fr/index.rst
diacamma/pro/docs/fr/presentation.rst
diacamma/pro/locale/en/LC_MESSAGES/django.mo
diacamma/pro/locale/en/LC_MESSAGES/django.po
diacamma/pro/locale/fr/LC_MESSAGES/django.mo
diacamma/pro/locale/fr/LC_MESSAGES/django.po
diacamma_pro-2.7.1.25042413.dist-info/licenses/LICENSE
diacamma_pro-2.7.1.25042413.dist-info/METADATA
diacamma_pro-2.7.1.25042413.dist-info/WHEEL
diacamma_pro-2.7.1.25042413.dist-info/top_level.txt
diacamma_pro-2.7.1.25042413.dist-info/RECORD
